[
  {
    "header": "",
    "footer": "",
    "py/object": "model.group.Group",
    "id": null,
    "name": ""
  },
  {
    "header": "header#r )Z",
    "footer": "footer\\hPw",
    "py/object": "model.group.Group",
    "id": null,
    "name": "name)3'YG ~c5"
  },
  {
    "header": "header{ Z5 rd;hX>F",
    "footer": "footer1U3 fT`<W,& DV5AF",
    "py/object": "model.group.Group",
    "id": null,
    "name": "namev "
  },
  {
    "header": "headerL0hdF67-QV9",
    "footer": "footer7?Y!6 z~",
    "py/object": "model.group.Group",
    "id": null,
    "name": "name"
  },
  {
    "header": "header iz7Mr8jt>FSOKk\\",
    "footer": "footerK 3; P: {l0 $y>=]F|",
    "py/object": "model.group.Group",
    "id": null,
    "name": "name"
  },
  {
    "header": "headerx'Uj^lL!$<`%KWyn wU",
    "footer": "footers k7qaq \"{4]k*h1]G",
    "py/object": "model.group.Group",
    "id": null,
    "name": "namekp"
  }
]